odoo/addons/base_import_async/README.rst
odoo/addons/base_import_async/__init__.py
odoo/addons/base_import_async/__manifest__.py
odoo/addons/base_import_async/i18n/base_import_async.pot
odoo/addons/base_import_async/i18n/fr.po
odoo/addons/base_import_async/i18n/pt.po
odoo/addons/base_import_async/models/__init__.py
odoo/addons/base_import_async/models/base_import_import.py
odoo/addons/base_import_async/models/queue_job.py
odoo/addons/base_import_async/readme/CONTRIBUTORS.rst
odoo/addons/base_import_async/readme/DESCRIPTION.rst
odoo/addons/base_import_async/readme/HISTORY.rst
odoo/addons/base_import_async/readme/ROADMAP.rst
odoo/addons/base_import_async/readme/USAGE.rst
odoo/addons/base_import_async/static/description/icon.png
odoo/addons/base_import_async/static/description/index.html
odoo/addons/base_import_async/static/src/js/import.js
odoo/addons/base_import_async/static/src/xml/import.xml
odoo/addons/base_import_async/views/base_import_async.xml
odoo12_addon_base_import_async-12.0.1.0.1.dist-info/METADATA
odoo12_addon_base_import_async-12.0.1.0.1.dist-info/WHEEL
odoo12_addon_base_import_async-12.0.1.0.1.dist-info/top_level.txt
odoo12_addon_base_import_async-12.0.1.0.1.dist-info/RECORD
